README.md
setup.cfg
setup.py
cloud_utils/__init__.py
cloud_utils/list_instances.py
cloud_utils.egg-info/PKG-INFO
cloud_utils.egg-info/SOURCES.txt
cloud_utils.egg-info/dependency_links.txt
cloud_utils.egg-info/entry_points.txt
cloud_utils.egg-info/not-zip-safe
cloud_utils.egg-info/requires.txt
cloud_utils.egg-info/top_level.txt