Metadata-Version: 1.0
Name: cloud-utils
Version: 1.0.40
Summary: Python Cloud Utilities
Home-page: https://github.com/google/python-cloud-utils
Author: Arie Abramovici
Author-email: beast@google.com
License: Copyright 2017 Google Inc.
